<?xml version="1.0" encoding="utf-8" ?>
<hibernate-mapping xmlns="urn:nhibernate-mapping-2.2" namespace="ZLERP.Model.Beton" assembly="ZLERP.Model">
  <class name="ZLERP.Model.Beton.B_BalanceDel, ZLERP.Model" table="B_BalanceDel" lazy="true"
    dynamic-insert="true" dynamic-update="true" batch-size="30" optimistic-lock="version">
    <id name="ID" column="ID">
      <generator class="native" />
    </id>
    <version name="Version" column="Version" />
    <property name="BaleBalanceID" column="BaleBalanceID" />
    <property name="ShipDocID" column="ShipDocID" />
    <property name="ModelType" column="ModelType" />
    <property name="BPrice" column="BPrice" />
    <property name="IPrice" column="IPrice" />
    <property name="TPrice" column="TPrice" />
    <property name="PPrice" column="PPrice" />
    <property name="CustBetonfee" column="CustBetonfee" />
    <property name="CustBetonNum" column="CustBetonNum" />
    <property name="OutTimeFee" column="OutTimeFee" />
    <property name="OutDistance" column="OutDistance" />
    <property name="OutDistanceFee" column="OutDistanceFee" />
    <property name="OtherFee" column="OtherFee" />
    <property name="CarBetonNum" column="CarBetonNum" />
    <property name="AllBMoney" column="AllBMoney" />
    <property name="AllIMoney" column="AllIMoney" />
    <property name="AllTMoney" column="AllTMoney" />
    <property name="AllPMoney" column="AllPMoney" />
    <property name="AllMoney" column="AllMoney" />
    <property name="Remark" column="Remark" />
    <property name="BuildTime" column="BuildTime" update="false"/>
    <property name="Builder" column="Builder" update="false"/>
    <property name="ModifyTime" column="ModifyTime" insert="false"/>
    <property name="Modifier" column="Modifier" insert="false"/>
    <property name="Lifecycle" column="Lifecycle" />
    <many-to-one name="ShippingDocument"  not-found="ignore">
      <column name="ShipDocID" sql-type="nvarchar" not-null="false" />
    </many-to-one>

    <many-to-one name="B_Balance"  not-found="ignore">
      <column name="BaleBalanceID" sql-type="nvarchar" not-null="false" />
    </many-to-one>
  </class>


</hibernate-mapping>